{
  "cli": {
    "version": ">=18.4.0",
    "appVersionSource": "remote"
  },
  "build": {
    "production": {
      "extends": "expo-production"
    },
    "expo-development": {
      "node": "22.18.0",
      "developmentClient": true,
      "distribution": "internal",
      "ios": {
        "simulator": true
      }
    },
    "expo-development-device": {
      "node": "22.18.0",
      "developmentClient": true,
      "distribution": "internal"
    },
    "expo-preview": {
      "node": "22.18.0",
      "distribution": "internal"
    },
    "expo-production": {
      "node": "22.18.0",
      "autoIncrement": true,
      "env": {
        "EXPO_PUBLIC_SUPABASE_URL": "https://jappgthiyedycwhttpcu.supabase.co",
        "EXPO_PUBLIC_SUPABASE_ANON_KEY": "eyJhbGciOiJIUzI1NiIsInR5cCI6IkpXVCJ9.eyJpc3MiOiJzdXBhYmFzZSIsInJlZiI6ImphcHBndGhpeWVkeWN3aHR0cGN1Iiwicm9sZSI6ImFub24iLCJpYXQiOjE3NjkyNDM0NzQsImV4cCI6MjA4NDgxOTQ3NH0.ztXAOOFh0AUuTBNDsvvVxcxncsKP4sju4AgfghvDNVc"
      }
    }
  },
  "submit": {
    "production": {
      "ios": {
        "ascAppId": "e070d995-b2f5-4b8e-8673-127727857f1d",
        "ascApiKeyId": "3873W42T27",
        "ascApiKeyIssuerId": "xxxxxxxx-xxxx-xxxx-xxxx-xxxxxxxxxxxx",
        "ascApiKeyPath": "./AuthKey_ABCD123456.p8"
      }
    },
    "expo-production": {
      "extends": "production"
    }
  }
}
